seekdb_lib/__init__.py
seekdb_lib/dummy.cpython-314-x86_64-linux-gnu.so
seekdb_lib/pyseekdb.so.0.gz
seekdb_lib-0.0.1.dev5.dist-info/METADATA
seekdb_lib-0.0.1.dev5.dist-info/WHEEL
seekdb_lib-0.0.1.dev5.dist-info/top_level.txt
seekdb_lib-0.0.1.dev5.dist-info/RECORD
